cached_llm/__init__.py
cached_llm/main.py
cached_llm-0.0.8.dist-info/METADATA
cached_llm-0.0.8.dist-info/WHEEL
cached_llm-0.0.8.dist-info/top_level.txt
cached_llm-0.0.8.dist-info/RECORD
