Metadata-Version: 2.4
Name: cached-llm
Version: 0.0.8
Requires-Python: >=3.11
Requires-Dist: diskcache>=5.6.3
Requires-Dist: openai>=1.101.0
